booyah/__init__.py
booyah/__main__.py
booyah/logger.py
booyah/bin/__init__.py
booyah/bin/booyah.py
booyah/config/__init__.py
booyah/config/routes.py
booyah/controllers/__init__.py
booyah/controllers/application_controller.py
booyah/controllers/home_controller.py
booyah/controllers/users_controller.py
booyah/db/__init__.py
booyah/db/adapters/__init__.py
booyah/db/adapters/base_adapter.py
booyah/db/adapters/postgresql_adapter.py
booyah/extensions/__init__.py
booyah/extensions/number.py
booyah/extensions/string.py
booyah/generators/__init__.py
booyah/generators/generate.py
booyah/generators/generate_new.py
booyah/generators/helpers/__init__.py
booyah/generators/helpers/io.py
booyah/generators/helpers/system_check.py
booyah/generators/templates/__init__.py
booyah/generators/templates/generate_new/__init__.py
booyah/generators/templates/generate_new/application.py
booyah/generators/templates/generate_new/app/__init__.py
booyah/generators/templates/generate_new/app/controllers/__init__.py
booyah/generators/templates/generate_new/app/controllers/application_controller.py
booyah/generators/templates/generate_new/app/models/__init__.py
booyah/generators/templates/generate_new/app/models/application_model.py
booyah/generators/templates/generate_new/config/__init__.py
booyah/generators/templates/generate_new/db/__init__.py
booyah/generators/templates/generate_new/templates/__init__.py
booyah/generators/templates/generate_new/templates/home/__init__.py
booyah/helpers/__init__.py
booyah/helpers/application_helper.py
booyah/helpers/controller_helper.py
booyah/models/__init__.py
booyah/models/application_model.py
booyah/models/model_query_builder.py
booyah/models/user.py
booyah/response/__init__.py
booyah/response/application_response.py
booyah/router/__init__.py
booyah/router/application_route.py
booyah/router/application_router.py
booyah/serializers/__init__.py
booyah/serializers/application_serializer.py
booyah/serializers/user_serializer.py
booyah/server/__init__.py
booyah-0.0.13.dist-info/LICENSE
booyah-0.0.13.dist-info/METADATA
booyah-0.0.13.dist-info/WHEEL
booyah-0.0.13.dist-info/entry_points.txt
booyah-0.0.13.dist-info/top_level.txt
booyah-0.0.13.dist-info/RECORD
