Metadata-Version: 2.1
Name: booyah
Version: 0.0.13
Summary: A joyful python web framework
Home-page: https://github.com/marceloribeiro/booyah
Author: Marcelo Ribeiro
Author-email: Marcelo Ribeiro <themarceloribeiro@gmail.com>
Project-URL: Homepage, https://github.com/marceloribeiro/booyah
Project-URL: Bug Tracker, https://github.com/marceloribeiro/booyah/issues
Classifier: Programming Language :: Python :: 3
Classifier: License :: OSI Approved :: MIT License
Classifier: Operating System :: OS Independent
Requires-Python: >=3.6
License-File: LICENSE
